DependiPy/__init__.py
DependiPy/archive.py
DependiPy/librarian.py
DependiPy/version.py
dependipy-2.1.7.dist-info/licenses/LICENSE
dependipy-2.1.7.dist-info/METADATA
dependipy-2.1.7.dist-info/WHEEL
dependipy-2.1.7.dist-info/entry_points.txt
dependipy-2.1.7.dist-info/top_level.txt
dependipy-2.1.7.dist-info/RECORD
