Metadata-Version: 2.4
Name: DependiPy
Version: 2.1.7
Home-page: https://github.com/ajacassi/DependiPy.git
Author: Andrea Jacassi
Author-email: 
License: MIT
License-File: LICENSE
Requires-Dist: argparse==1.4.0
Requires-Dist: tqdm==4.64.1
Requires-Dist: pandas==2.3.2
Requires-Dist: numpy==1.26.4
Dynamic: author
Dynamic: description
Dynamic: description-content-type
Dynamic: home-page
Dynamic: license
Dynamic: license-file
Dynamic: requires-dist
